{
  "response": [
     {
      "datetime": 1680248429, 
      "filename": "msm8953_64-incremental-eng.euler22.zip", 
      "id": "44ba3af198591853507339e63af39b1f", 
      "romtype": "BETA",
      "size": 325969, 
      "url": "https://github.com/mohancm-em/ota_host/releases/download/v1.0.0/msm8953_64-incremental-eng.euler22.zip", 
      "version": "v1.0.0",
      "changelog_system": "Incremental OTA test",
      "changelog_misc" : "updates to android 10",
      "changelog_device" : "fixed adb serialno",
      "changelog_settings" : "New UI",
      "changelog_securitypatch" : "Updated security patch to Mar 2023"
    }
  ]
}
